classfromtypeddict/__init__.py
classfromtypeddict/classfromtypeddict.py
classfromtypeddict-0.0.5.dist-info/licenses/LICENSE
classfromtypeddict-0.0.5.dist-info/METADATA
classfromtypeddict-0.0.5.dist-info/WHEEL
classfromtypeddict-0.0.5.dist-info/top_level.txt
classfromtypeddict-0.0.5.dist-info/RECORD
